ast_monitor/__init__.py
ast_monitor/basic_data.py
ast_monitor/digital_twin.py
ast_monitor/goals_processor.py
ast_monitor/gps_sensor.py
ast_monitor/hr_sensor.py
ast_monitor/html_request_handler.py
ast_monitor/icons/arrow_down.svg
ast_monitor/icons/arrow_left.svg
ast_monitor/icons/arrow_right.svg
ast_monitor/icons/arrow_up.svg
ast_monitor/icons/ascent.svg
ast_monitor/icons/bicycle.svg
ast_monitor/icons/clock.svg
ast_monitor/icons/distance.svg
ast_monitor/icons/heart.svg
ast_monitor/icons/licence.txt
ast_monitor/icons/play.svg
ast_monitor/icons/shutdown.svg
ast_monitor/icons/speed.svg
ast_monitor/icons/stop.svg
ast_monitor/interval_training.py
ast_monitor/mainwindow.py
ast_monitor/map/README.md
ast_monitor/map/env.d.ts
ast_monitor/map/index.html
ast_monitor/map/package-lock.json
ast_monitor/map/package.json
ast_monitor/map/public/favicon.ico
ast_monitor/map/src/App.vue
ast_monitor/map/src/assets/base.css
ast_monitor/map/src/assets/logo.svg
ast_monitor/map/src/assets/main.css
ast_monitor/map/src/components/DisplayCard.vue
ast_monitor/map/src/components/Map.vue
ast_monitor/map/src/components/RouteProgress.vue
ast_monitor/map/src/components/TrainingMetrics.vue
ast_monitor/map/src/components/WelcomeItem.vue
ast_monitor/map/src/components/icons/IconCommunity.vue
ast_monitor/map/src/components/icons/IconDocumentation.vue
ast_monitor/map/src/components/icons/IconEcosystem.vue
ast_monitor/map/src/components/icons/IconSupport.vue
ast_monitor/map/src/components/icons/IconTooling.vue
ast_monitor/map/src/main.ts
ast_monitor/map/src/stores/counter.ts
ast_monitor/map/tsconfig.app.json
ast_monitor/map/tsconfig.json
ast_monitor/map/tsconfig.node.json
ast_monitor/map/vite.config.ts
ast_monitor/model.py
ast_monitor/route_reader.py
ast_monitor/simulation.py
ast_monitor/training_session.py
ast_monitor/write_log.py
ast_monitor-0.5.5.dist-info/LICENSE
ast_monitor-0.5.5.dist-info/METADATA
ast_monitor-0.5.5.dist-info/WHEEL
ast_monitor-0.5.5.dist-info/RECORD
