Metadata-Version: 2.1
Name: ast_monitor
Version: 0.5.5
Summary: AST-Monitor is a wearable Raspberry Pi computer for cyclists
Home-page: https://github.com/firefly-cpp/AST-Monitor
License: MIT
Keywords: artificial sport trainer,computational intelligence,data mining,datasets,digital twin,optimization,sport activities,tcx
Author: Iztok Fister Jr.
Author-email: iztok@iztok-jr-fister.eu
Requires-Python: >=3.9,<4.0
Classifier: License :: OSI Approved :: MIT License
Classifier: Programming Language :: Python :: 3
Classifier: Programming Language :: Python :: 3.9
Classifier: Programming Language :: Python :: 3.10
Classifier: Programming Language :: Python :: 3.11
Classifier: Programming Language :: Python :: 3.12
Requires-Dist: PyQt6 (==6.4.2)
Requires-Dist: PyQt6-WebEngine (>=6.5.0,<7.0.0)
Requires-Dist: geopy
Requires-Dist: matplotlib
Requires-Dist: openant (>=1.2.0,<2.0.0)
Requires-Dist: pyqt-feedback-flow (>=0.3.4,<0.4.0)
Requires-Dist: sport-activities-features (>=0.5.0,<0.6.0)
Requires-Dist: tcxreader (>=0.4.2,<0.5.0)
Project-URL: Documentation, https://ast-monitor.readthedocs.io/en/latest/
Project-URL: Repository, https://github.com/firefly-cpp/AST-Monitor
